basicmathw/__init__.py
basicmathw/operations.py
basicmathw-0.1.0.dist-info/LICENSE
basicmathw-0.1.0.dist-info/METADATA
basicmathw-0.1.0.dist-info/WHEEL
basicmathw-0.1.0.dist-info/top_level.txt
basicmathw-0.1.0.dist-info/RECORD
